[{"line":1,"elements":[{"start_timestamp":"2026-02-02T12:00:01.694Z","before":[{"result":{"duration":3603624700,"status":"passed"},"match":{"location":"Hooks.Hooks.setup()"}}],"line":3,"name":"Registered user completes a purchase","description":"","id":"add-product-to-cart;registered-user-completes-a-purchase","after":[{"result":{"duration":247124900,"status":"passed"},"match":{"location":"Hooks.Hooks.tearDown()"}}],"type":"scenario","keyword":"Scenario","steps":[{"result":{"duration":3224349400,"status":"passed"},"line":4,"name":"the user is a registered user","match":{"location":"stepdefinitions.stepDefinition.register()"},"keyword":"Given "},{"result":{"duration":4281618100,"status":"passed"},"line":5,"name":"the user logs in","match":{"location":"stepdefinitions.stepDefinition.login()"},"keyword":"When "},{"result":{"duration":4765621700,"status":"passed"},"line":6,"name":"adds a product to the cart","match":{"location":"stepdefinitions.stepDefinition.addProduct()"},"keyword":"And "},{"result":{"duration":19116024600,"status":"passed"},"line":7,"name":"the user checks out successfully","match":{"location":"stepdefinitions.stepDefinition.checkoutFlow()"},"keyword":"Then "}]}],"name":"Add product to cart","description":"","id":"add-product-to-cart","keyword":"Feature","uri":"file:src/test/resources/features/add_to_cart.feature","tags":[]}]